cloudkube/ClusterManager.py
cloudkube/__init__.py
cloudkube/clusterConfig.py
cloudkube/depre_teardownCluster.py
cloudkube/entry.py
cloudkube/main.py
cloudkube/utils.py
cloudkube/commands/__init__.py
cloudkube/commands/configure_kubectl.py
cloudkube/commands/install_efs_csi_driver.py
cloudkube/commands/install_ingress.py
cloudkube/commands/remove_efs_csi_driver.py
cloudkube/commands/remove_ingress.py
cloudkube/displayUtils/__init__.py
cloudkube/displayUtils/display.py
cloudkube/terraform/main.tf
cloudkube/terraform/outputs.tf
cloudkube/terraform/terraform.tf
cloudkube/terraform/terraform.tfstate
cloudkube/terraform/terraform.tfstate.backup
cloudkube-0.16.6.dist-info/LICENSE
cloudkube-0.16.6.dist-info/METADATA
cloudkube-0.16.6.dist-info/WHEEL
cloudkube-0.16.6.dist-info/entry_points.txt
cloudkube-0.16.6.dist-info/top_level.txt
cloudkube-0.16.6.dist-info/RECORD
