Metadata-Version: 2.2
Name: cloudkube
Version: 0.16.6
Summary: minikube for the cloud
Author: Chan Ming Han
Requires-Python: >=3.11
License-File: LICENSE
Requires-Dist: boto3
Requires-Dist: python_terraform
Requires-Dist: kubernetes
Requires-Dist: requests
Requires-Dist: GitPython
Dynamic: author
Dynamic: requires-dist
Dynamic: requires-python
Dynamic: summary
